Metadata-Version: 2.1
Name: console-color-writer
Version: 1.0.1
Summary: write lines with color and tags ! 
Home-page: UNKNOWN
Author: clever chen
Author-email: 
License: UNKNOWN
Keywords: python,console_color_writer,windows,mac,linux
Platform: UNKNOWN
Classifier: Development Status :: 1 - Planning
Classifier: Intended Audience :: Developers
Classifier: Programming Language :: Python :: 3
Classifier: Operating System :: Unix
Classifier: Operating System :: MacOS :: MacOS X
Classifier: Operating System :: Microsoft :: Windows
